main.py
jinja_max-0.1.0.dist-info/METADATA
jinja_max-0.1.0.dist-info/WHEEL
jinja_max-0.1.0.dist-info/entry_points.txt
jinja_max-0.1.0.dist-info/top_level.txt
jinja_max-0.1.0.dist-info/RECORD
