Metadata-Version: 2.4
Name: jinja-max
Version: 0.1.0
Summary: Add your description here
Requires-Python: >=3.12
Requires-Dist: jinja2>=3.1.6
Requires-Dist: typer>=0.16.0
